flet_extended_interactive_viewer/__init__.py
flet_extended_interactive_viewer/flet_extended_interactive_viewer.py
flutter/flet_extended_interactive_viewer/CHANGELOG.md
flutter/flet_extended_interactive_viewer/LICENSE
flutter/flet_extended_interactive_viewer/README.md
flutter/flet_extended_interactive_viewer/pubspec.lock
flutter/flet_extended_interactive_viewer/pubspec.yaml
flutter/flet_extended_interactive_viewer/lib/flet_extended_interactive_viewer.dart
flutter/flet_extended_interactive_viewer/lib/src/create_control.dart
flutter/flet_extended_interactive_viewer/lib/src/flet_extended_interactive_viewer.dart
flet_extended_interactive_viewer-0.1.2.dist-info/METADATA
flet_extended_interactive_viewer-0.1.2.dist-info/WHEEL
flet_extended_interactive_viewer-0.1.2.dist-info/top_level.txt
flet_extended_interactive_viewer-0.1.2.dist-info/RECORD
