Metadata-Version: 2.4
Name: flet-extended-interactive-viewer
Version: 0.1.2
Summary: Flet-Extended-Interactive-Viewer is a Flet control that provides multiple customization options for displaying two-dimensional content.
Author-email: Florian Hock <fhock2002@gmail.com>
Project-URL: Homepage, https://github.com/PraiseTheDarkFlo/flet-extended-interactive-viewer
Project-URL: Documentation, https://praisethedarkflo.github.io/flet-extended-interactive-viewer/
Project-URL: Repository, https://github.com/PraiseTheDarkFlo/flet-extended-interactive-viewer
Project-URL: Issues, https://github.com/PraiseTheDarkFlo/flet-extended-interactive-viewer/issues
Requires-Python: >=3.9
Requires-Dist: flet>=0.28.3
